{
  "project_info": {
    "project_number": "441591754986",
    "project_id": "test01-b2875",
    "storage_bucket": "test01-b2875.appspot.com"
  },
  "client": [
    {
      "client_info": {
        "mobilesdk_app_id": "1:441591754986:android:cb18fcfbed101f0bb8e793",
        "android_client_info": {
          "package_name": "com.example.test01"
        }
      },
      "oauth_client": [
        {
          "client_id": "441591754986-3l823v8nfk6noofcp900l062b23dii8c.apps.googleusercontent.com",
          "client_type": 3
        }
      ],
      "api_key": [
        {
          "current_key": "AIzaSyABxzL7NJaGrJrf_SndvfgpJJygz91hUeo"
        }
      ],
      "services": {
        "appinvite_service": {
          "other_platform_oauth_client": [
            {
              "client_id": "441591754986-3l823v8nfk6noofcp900l062b23dii8c.apps.googleusercontent.com",
              "client_type": 3
            }
          ]
        }
      }
    }
  ],
  "configuration_version": "1"
}